zaheerjk/__init__.py
zaheeruddin-0.1.0.dist-info/METADATA
zaheeruddin-0.1.0.dist-info/WHEEL
zaheeruddin-0.1.0.dist-info/top_level.txt
zaheeruddin-0.1.0.dist-info/RECORD
