Metadata-Version: 2.4
Name: zaheeruddin
Version: 0.1.0
Summary: Personal and professional profile module of Mohd Zaheeruddin
Home-page: https://github.com/mdzaheerjk/zaheerjk
Author: Mohd Zaheeruddin
Author-email: info.zaheerjk@gmail.com
License: MIT
Keywords: zaheerjk profile education ai ml
Classifier: Development Status :: 4 - Beta
Classifier: Intended Audience :: Education
Classifier: Programming Language :: Python :: 3
Classifier: License :: OSI Approved :: MIT License
Dynamic: author
Dynamic: author-email
Dynamic: classifier
Dynamic: description
Dynamic: description-content-type
Dynamic: home-page
Dynamic: keywords
Dynamic: license
Dynamic: summary
